noaa_ftp/__init__.py
noaa_ftp/noaa/__init__.py
noaa_ftp-0.1.11.dist-info/WHEEL
noaa_ftp-0.1.11.dist-info/METADATA
noaa_ftp-0.1.11.dist-info/RECORD
