Metadata-Version: 2.1
Name: noaa-ftp
Version: 0.1.11
Summary: A python package to work with NOAA FTP
Home-page: https://github.com/javad-rzvn/noaa_ftp
Keywords: noaa,ftp
Author: javad-rzvn
Author-email: javad.rezvanpour@gmail.com
Requires-Python: >=3.7,<4.0
Classifier: Programming Language :: Python :: 3
Classifier: Programming Language :: Python :: 3.10
Classifier: Programming Language :: Python :: 3.7
Classifier: Programming Language :: Python :: 3.8
Classifier: Programming Language :: Python :: 3.9
Requires-Dist: progressbar2 (>=4.0.0,<5.0.0)
Project-URL: Repository, https://github.com/javad-rzvn/noaa_ftp
